setup.py
owdo/__init__.py
owdo/command_line.py
owdo/connection.py
owdo/core.py
owdo/raw.py
owdo/types.py
owdo/util.py
owdo.egg-info/PKG-INFO
owdo.egg-info/SOURCES.txt
owdo.egg-info/dependency_links.txt
owdo.egg-info/entry_points.txt
owdo.egg-info/requires.txt
owdo.egg-info/top_level.txt
owdo.egg-info/zip-safe