Metadata-Version: 1.0
Name: owdo
Version: 0.3
Summary: opsworks do
Home-page: UNKNOWN
Author: Justin Alan Ryan
Author-email: bitmonk@icloud.com
License: AGPL2
Keywords: aws opsworks boto
Platform: UNKNOWN
